cmoordyn.cpython-312-darwin.so
wrappers/python/moordyn/moordyn.py
wrappers/python/moordyn/__init__.py
wrappers/python/moordyn/moorpyic.py
wrappers/python/moordyn/Generator/Body.py
wrappers/python/moordyn/Generator/Option.py
wrappers/python/moordyn/Generator/Line.py
wrappers/python/moordyn/Generator/__init__.py
wrappers/python/moordyn/Generator/Point.py
wrappers/python/moordyn/Generator/Mooring.py
wrappers/python/moordyn/Generator/Failure.py
wrappers/python/moordyn/Generator/Rod.py
wrappers/python/moordyn/Generator/Entity.py
wrappers/python/moordyn/Generator/Intro.py
bench/Mooring/cases/generate_cases.py
moordyn/moordyn.py
moordyn/__init__.py
moordyn/moorpyic.py
moordyn/.dylibs/libmoordyn.2.4.dylib
moordyn/Generator/Body.py
moordyn/Generator/Option.py
moordyn/Generator/Line.py
moordyn/Generator/__init__.py
moordyn/Generator/Point.py
moordyn/Generator/Mooring.py
moordyn/Generator/Failure.py
moordyn/Generator/Rod.py
moordyn/Generator/Entity.py
moordyn/Generator/Intro.py
moordyn-2.4.0.dist-info/RECORD
moordyn-2.4.0.dist-info/WHEEL
moordyn-2.4.0.dist-info/top_level.txt
moordyn-2.4.0.dist-info/METADATA
moordyn-2.4.0.dist-info/licenses/LICENSE.txt
