Metadata-Version: 2.4
Name: moordyn
Version: 2.4.0
Summary: Python wrapper for MoorDyn library
Author-email: Jose Luis Cercos-Pita <jlc@core-marine.com>
Project-URL: Homepage, https://github.com/FloatingArrayDesign/MoorDyn
Project-URL: Bug Tracker, https://github.com/FloatingArrayDesign/MoorDyn/issues
Project-URL: Documentation, https://moordyn.readthedocs.io
Classifier: Programming Language :: Python :: 3
Classifier: License :: OSI Approved :: BSD License
Classifier: Operating System :: OS Independent
Requires-Python: >=3.7
License-File: LICENSE.txt
Dynamic: license-file
